{
  "url": "https://vnexpress.net/cau-thu-viet-nam-phu-nhan-bat-tay-malaysia-de-loai-indonesia-4991766.html",
  "title": "Cầu thủ Việt Nam phủ nhận 'bắt tay' Malaysia để loại Indonesia",
  "date": "Thứ ba, 9/12/2025, 16:43 (GMT+7)",
  "description": "Thái Lan Tiền vệ Nguyễn Thái Quốc Cường khẳng định Việt Nam đặt mục tiêu chiến thắng chứ không chủ hoà Malaysia ở lượt cuối bảng B bóng đá nam SEA Games 33",
  "content": "Cầu thủ Việt Nam phủ nhận bắt tay Malaysia để loại Indonesia Thái Lan Tiền vệ Nguyễn Thái Quốc Cường khẳng định Việt Nam đặt mục tiêu chiến thắng chứ không chủ hoà Malaysia ở lượt cuối bảng B bóng đá nam SEA Games 33 Hôm qua Indonesia thua sốc Philippines 0 1 ở lượt hai bảng C Điều đó đồng nghĩa với việc đội đương kim vô địch chỉ có thể giành tối đa ba điểm và phải cạnh tranh một suất vé vớt cho vị trí nhì bảng xuất sắc Họ sẽ đá lượt cuối vòng bảng gặp Myanmar ngày 11 12 Tuy nhiên nếu ở lượt cuối bảng B vào ngày 11 12 Việt Nam hòa Malaysia để cùng có bốn điểm Indonesia sẽ bị loại Do không còn quyền tự quyết HLV Indra Sjafri thừa nhận không thể làm gì nếu Malaysia và Việt Nam bắt tay hòa nhau Tiền vệ Nguyễn Thái Quốc Cường tập luyện cùng U22 Việt Nam ở sân bóng thuộc trường Đại học RBAC ở Bangkok Thái Lan ngày 9 12 2025 Ảnh Hiếu Lương Tuy nhiên khi được hỏi về vấn đề này tiền vệ Nguyễn Thái Quốc Cường khẳng định Việt Nam sẽ chơi hết mình Mục tiêu của chúng tôi gặp Malaysia là không có hòa phải thắng anh nói trước buổi tập tại sân bóng thuộc Đại học RBAC ở Bangkok chiều nay Chìa khóa để chiến thắng là tinh thần quyết tâm thái độ thi đấu tốt và đoàn kết Việt Nam đang thể hiện tốt điều ấy Nếu hòa Malaysia Việt Nam chỉ có thể đứng nhì bảng B do kém hiệu số bàn thắng thua Theo sổ tay kỹ thuật bóng đá SEA Games 33 đội nhì có thành tích tốt nhất sẽ gặp đội nhất bảng A nhiều khả năng là chủ nhà Thái Lan Quốc Cường sinh năm 2004 ở Nghệ An nhưng sớm chuyển vào Đồng Nai cùng gia đình Năm 2014 anh gia nhập Học viện Nutifood từng chơi giải hạng Ba năm 2022 cho đội bóng này rồi hạng Nhất 2023 cho Bà Rịa Vũng Tàu Từ tháng 8 2024 Quốc Cường gia nhập CLB TP HCM nay là Công an TP HCM Ở cấp đội tuyển Quốc Cường có mặt ở nhiều đợt tập trung các cấp độ tuyển trẻ nhưng chưa được dự các giải chính thức Việc anh được dự SEA Games 33 một phần nhờ việc tiền vệ Nguyễn Văn Trường gặp chấn thương nặng Quốc Cường là em họ của tiền đạo nổi tiếng Nguyễn Công Phượng Anh khẳng định không gặp áp lực nào về chuyện này ngược lại cảm thấy tự hào cho bản thân và gia đình Anh Phượng luôn động viên chỉ ra những thiếu sót và lỗi để tôi cải thiện Quốc Cường cho hay Việt Nam đang duy trì lịch tập một buổi mỗi ngày trước khi quyết chiến Malaysia vào lúc 16h ngày 11 12 Cùng giờ tuyển nữ Việt Nam có trận đấu quyết định với Myanmar ở lượt cuối bảng B tại Chonburi Đội bóng của HLV Mai Đức Chung phải thắng mới chắc chắn giành vé vào bán kết Quốc Cường cho biết đội U22 đã xem trận nữ Việt Nam thua Philippines 0 1 hôm qua Anh cảm thấy tiếc vì bàn thua ở phút cuối đồng thời cho rằng đội nhà đã bị tước một quả phạt đền vì lỗi chạm tay trước đó Anh hy vọng cả hai đội tuyển của Việt Nam sẽ cùng hoàn thành mục tiêu giành vé đi tiếp Hiếu Lương"
}